[
  {"tekst": ""},
  {"tekst": "Kiedy rum zaszumi w głowie, ",
   "chwyty: ["a"]},
  {"tekst": "Cały świat nabiera treści, ",
   "chwyty": ["G"]},
  {"tekst": "Wtedy chętnie słucha człowiek",
   "chwyty": ["a", "C"]},
  {"tekst": "Morskich opowieści.",
   "chwyty": ["G", "E7", "a"]},
  {"tekst": ""},
  {"tekst": "Ref.: Hej, ha! Kolejkę nalej!"},
  {"tekst": "Hej, ha! Kielichy wznieśmy!"},
  {"tekst": "To zrobi doskonale"},
  {"tekst": "Morskim opowieściom."},
  {"tekst": ""},
  {"tekst": "Kto chce, to niechaj słucha,"},
  {"tekst": "Kto nie chce, niech nie słucha,"},
  {"tekst": "Jak balsam są dla ucha"},
  {"tekst": "Morskie opowieści."},
  {"tekst": ""},
  {"tekst": "Kto chce, to niechaj wierzy,"},
  {"tekst": "Kto nie chce, niech nie wierzy,"},
  {"tekst": "Nam na tym nie zależy,"},
  {"tekst": "Więc wypijmy jeszcze."},
  {"tekst": ""},
  {"tekst": "Łajba to jest morski statek,"},
  {"tekst": "Sztorm to wiatr, co dmucha z gestem,"},
  {"tekst": "Cierpi kraj na niedostatek"},
  {"tekst": "Morskich opowieści."},
  {"tekst": ""},
  {"tekst": "Pływał raz marynarz, który"},
  {"tekst": "Żywił się wyłącznie pieprzem,"},
  {"tekst": "Sypał pieprz do konfitury"},
  {"tekst": "I do zupy mlecznej."},
  {"tekst": ""},
  {"tekst": "Może ktoś się bardzo zżymał,"},
  {"tekst": "Mówiąc, że to zdrożne wieści,"},
  {"tekst": "Ale to jest właśnie klimat"},
  {"tekst": "Morskich opowieści."},
  {"tekst": ""},
  {"tekst": "Kto chce, ten niechaj wierzy,"},
  {"tekst": "Kto nie chce, niech nie wierzy,"},
  {"tekst": "Nam na tym nie zależy,"},
  {"tekst": "Więc wypijmy jeszcze"},
  {"tekst": ""},
  {"tekst": "Był na Lwowie raz praktykant,"},
  {"tekst": "Dwumetrowy wielki taki,"},
  {"tekst": "przy kotwicznym kabestanie,"},
  {"tekst": "Połamał handszpaki."},
  {"tekst": ""},
  {"tekst": "Kolumb odkrył Amerykę,"},
  {"tekst": "Kiedy ścigał się z Halikiem,"},
  {"tekst": "Indianie się zarzekali,"},
  {"tekst": "Że pierwszy był Halik."},
  {"tekst": ""},
  {"tekst": "O wyprawie wokół globu,"},
  {"tekst": "Też fałszywe są pogłoski,"},
  {"tekst": "Pierwszy żaden tam Magellan,"},
  {"tekst": "Tylko Baranowski."},
  {"tekst": ""},
  {"tekst": "Znałem kiedyś kapitana"},
  {"tekst": "wielki był wielbiciel sportu"},
  {"tekst": "Stawiał żagle na fujarze"},
  {"tekst": "I wychodził z portu"},
  {"tekst": ""},
  {"tekst": "Rudy Bronek, kiedy popił,"},
  {"tekst": "Robił bardzo groźne miny,"},
  {"tekst": "W Sztokholmie skakał"},
  {"tekst": "do wody i gonił rekiny."},
  {"tekst": ""},
  {"tekst": "I choć rekin twarda sztuka,"},
  {"tekst": "Ale Bronek w wielkiej złości"},
  {"tekst": "Łapał gada za ogona"},
  {"tekst": "I mu łamał kości"},
  {"tekst": ""},
  {"tekst": "W trakcie postoju w porcie kapitan wypadł do wody kiedy pomagali jemu wyjść na pokład"},
  {"tekst": "na pytanie czego tam szukał odpowiedział “goniłem rekina”."},
  {"tekst": ""},
  {"tekst": "Był na “Gwarku” raz oficer"},
  {"tekst": "Krewną swą ze sobą włóczył"},
  {"tekst": "Targał ja po całym jachcie"},
  {"tekst": "Wachcie swej poruczył"},
  {"tekst": ""},
  {"tekst": "Był na “Gwarku” młodszy majtek"},
  {"tekst": "Miał „carmeny” do wąchania,"},
  {"tekst": "„Sporty” zabrał do palenia"},
  {"tekst": "Gitarę do grania."},
  {"tekst": ""},
  {"tekst": "Małysz siedzi już na belce,"},
  {"tekst": "Patrzy ze spokojem z góry,"},
  {"tekst": "Jak się wkurwi to doleci"},
  {"tekst": "Na same Mazury."},
  {"tekst": ""},
  {"tekst": "Raz na Zegrzu była flauta,"},
  {"tekst": "Nagle w żagle coś nam dmucha,"},
  {"tekst": "A to płuca nadweręża"},
  {"tekst": "Włodek Zawierucha."},
  {"tekst": ""},
  {"tekst": "Kto chce, ten niechaj wierzy,"},
  {"tekst": "Kto nie chce, niech nie słucha."},
  {"tekst": "Kto najlepszym KWŻ-etem?"},
  {"tekst": "Włodek Zawierucha."},
  {"tekst": ""},
  {"tekst": "Bosman portu \"harleyowiec\","},
  {"tekst": "Co się na nas zawsze złościł,"},
  {"tekst": "W nodze, po licznych wypadkach"},
  {"tekst": "Ma plastik, nie kości."},
  {"tekst": ""},
  {"tekst": "Na jeziora wypłynęła"},
  {"tekst": "Galera z galerniczkami"},
  {"tekst": "Strzegł tam władzy kapitana"},
  {"tekst": "“Kot z pięcioma ogonami”"},
  {"tekst": ""},
  {"tekst": "Gdy któraś coś źle zrobiła,"},
  {"tekst": "Wieczorem przy całej grupie,"},
  {"tekst": "Brał kapitan w rękę “kota’."},
  {"tekst": "Bił po gołej pupie."},
  {"tekst": ""},
  {"tekst": "Rączka na niej pięć rzemyków"},
  {"tekst": "Dość “niewinnie” wyglądało"},
  {"tekst": "Lecz na mokrą goła pupę"},
  {"tekst": "Naprawdę bolało"},
  {"tekst": ""},
  {"tekst": "Kiedy robiąc zwrot przez rufę"},
  {"tekst": "Jolka grota nie wybrała"},
  {"tekst": "To na apelu wieczornym"},
  {"tekst": "Trzy “koty” dostała"},
  {"tekst": ""},
  {"tekst": "Basia idąc do “człowieka”"},
  {"tekst": "wykonała wiele zwrotów"},
  {"tekst": "i na apelu wieczornym"},
  {"tekst": "dostała sześć “kotów”"},
  {"tekst": ""},
  {"tekst": "Przy podejściu do pomostu."},
  {"tekst": "Kasia dziobem uderzyła"},
  {"tekst": "Za to po zachodzie słońca."},
  {"tekst": "Dupcia w pręgach była."},
  {"tekst": ""},
  {"tekst": "Zapytacie galerniczek"},
  {"tekst": "Czy te razy się przydały"},
  {"tekst": "tak, bo kiedy był egzamin"},
  {"tekst": "Wszystkie dobrze zdały"},
  {"tekst": ""},
  {"tekst": "Nelson, angielski Admirał,"},
  {"tekst": "Strzeliłby se w łeb i kwita,"},
  {"tekst": "Gdyby wiedział co dokonał,"},
  {"tekst": "Kloss, zwykły kapitan."},
  {"tekst": ""},
  {"tekst": "Kloss uciekał Niemcom zawsze"},
  {"tekst": "Nigdy jego nie złapali"},
  {"tekst": "A dorównać mu potrafił"},
  {"tekst": "Jedynie pies Szarik"},
  {"tekst": ""},
  {"tekst": "U sąsiadów w Ukrainie"},
  {"tekst": "W Czernobylu pierdyknęło,"},
  {"tekst": "Elektrownia wyleciała"},
  {"tekst": "Pół miasta zginęło"},
  {"tekst": ""},
  {"tekst": "Ruscy chcieli to zataić"},
  {"tekst": "Nikt nie wiedział co się dzieje"},
  {"tekst": "Ale Szwedzi wyczaili"},
  {"tekst": "I się lugol leje"},
  {"tekst": ""},
  {"tekst": "Ref.: Hej, ha, lugola nalej,"},
  {"tekst": "Hej, ha, probówki wznieśmy,"},
  {"tekst": "Na chorobę popromienną,"},
  {"tekst": "Jest to lek najlepszy."},
  {"tekst": ""},
  {"tekst": "Bracia nic nie powiedzieli,"},
  {"tekst": "Myśleli, że się rozwieje,"},
  {"tekst": "Ale Szwedzi namierzyli,"},
  {"tekst": "Już się lugol leje."},
  {"tekst": ""},
  {"tekst": "Ciągle straszą nas Reganem,"},
  {"tekst": "Rakietami i kosmosem,"},
  {"tekst": "A tu bracia robią prezent"},
  {"tekst": "Pod samiutkim nosem."},
  {"tekst": ""},
  {"tekst": "Kiedy tylko coś tam gruchnie,"},
  {"tekst": "Wschodni wiatr ku nam zawieje,"},
  {"tekst": "Wtedy każdy chętnie spieprza"},
  {"tekst": "W niedostępną knieję."},
  {"tekst": ""},
  {"tekst": "Na Podlasiu się rozeszła"},
  {"tekst": "Wieść, co przyszła prosto z pola:"},
  {"tekst": "Chodźcie ludzie do ośrodka,"},
  {"tekst": "Dają tam lugola."},
  {"tekst": ""},
  {"tekst": "Krów na łące paść nie można,"},
  {"tekst": "Choć stężenie ciągle spada,"},
  {"tekst": "TASS agencja przecież wszędzie"},
  {"tekst": "Ciągle o tym gada."},
  {"tekst": ""},
  {"tekst": "Pierwszy Maja - Święto Pracy,"},
  {"tekst": "Na ulicach tłum wariuje,"},
  {"tekst": "A tu miłość od przyjaciół"},
  {"tekst": "Ciągle promieniuje."},
  {"tekst": ""},
  {"tekst": "Kiedy włosy mi wypadną"},
  {"tekst": "I biegunka mną zawładnie,"},
  {"tekst": "Co ja wtedy sobie myślę,"},
  {"tekst": "Tego nikt nie zgadnie."},
  {"tekst": ""},
  {"tekst": "W głowie coś mi strasznie łupie,"},
  {"tekst": "Skóra schodzi też płatami,"},
  {"tekst": "Lecz Ty miej to wszystko w dupie,"},
  {"tekst": "Śpiewaj razem z nami."},
  {"tekst": ""},
  {"tekst": "Kiedy zęby Ci wylecą,"},
  {"tekst": "Łysa pała Ci zostanie,"},
  {"tekst": "Wspomnisz Bracie dawne czasy,"},
  {"tekst": "Hej, lugola nalej!"},
  {"tekst": ""},
  {"tekst": "Pij lugola, pij na zdrowie,"},
  {"tekst": "To się może przydać jeszcze,"},
  {"tekst": "Bo w Żarnowcu już budują,"},
  {"tekst": "Skończą za lat dwieście."},
  {"tekst": ""},
  {"tekst": "Na Europę padł strach blady,"},
  {"tekst": "Co sprytniejszy schron buduje,"},
  {"tekst": "Płaszcz gumowy na się wkłada,"},
  {"tekst": "Mleka nie kupuje."},
  {"tekst": ""},
  {"tekst": "A ja przecież wdzięczny jestem,"},
  {"tekst": "W sercu się zabliźnia rana,"},
  {"tekst": "Że mi zginąć nie pozwolą"},
  {"tekst": "Od rakiet Reagana."},
  {"tekst": ""},
  {"tekst": "Pływał sobie kleryk, który"},
  {"tekst": "Myślał, że go dupa boli,"},
  {"tekst": "Patrzy, a tu arcybiskup"},
  {"tekst": "W koi go pierdoli."},
  {"tekst": ""},
  {"tekst": "Aby o arcybiskupie"},
  {"tekst": "Naród długo nie pamiętał."},
  {"tekst": "Zaraz na pożarcie jemu"},
  {"tekst": "Dali dyrygenta"},
  {"tekst": ""},
  {"tekst": "Jak spod Helu raz dmuchnęło,"},
  {"tekst": "Żagle zdarła moc nadludzka,"},
  {"tekst": "Patrzę - w koje mi przywiało"},
  {"tekst": "Nagą babkę z Pucka."},
  {"tekst": ""},
  {"tekst": "Niech drżą gitary struny,"},
  {"tekst": "Niech wiatr grzywacze pieści,"},
  {"tekst": "Gdy płyniemy pod banderą"},
  {"tekst": "Morskich opowieści."},
  {"tekst": ""},
  {"tekst": "Był na \"Lwowie\" młody majtek,"},
  {"tekst": "Co nie ruchał przez rok chyba,"},
  {"tekst": "i wytryskiem swojej spermy"},
  {"tekst": "Zabił wieloryba"},
  {"tekst": ""},
  {"tekst": "Raz bosmana rekin pożarł,"},
  {"tekst": "Lecz nie smućcie się kochani,"},
  {"tekst": "Bosman żyje, rekin umarł,"},
  {"tekst": "Zatruł się zbukami."},
  {"tekst": ""},
  {"tekst": "Kiedy bosman trypra złapał,"},
  {"tekst": "Obciął sobie własnym nożem,"},
  {"tekst": "A gdy rzucił go za burtę,"},
  {"tekst": "To wezbrało morze."},
  {"tekst": ""},
  {"tekst": "Hej bo wesoły uśmiech,"},
  {"tekst": "W czas burzy jest pogodą,"},
  {"tekst": "Uśmiech ku brzegom pędzi,"},
  {"tekst": "Rozgniewaną wodę."},
  {"tekst": ""},
  {"tekst": "Żagiel mój burzę niejedną przetrwał,"},
  {"tekst": "Nie raz nad głową wiatr kłębił chmury,"},
  {"tekst": "Bardziej o fajke dbam, by nie zgasła,"},
  {"tekst": "Niz o własną skórę."},
  {"tekst": ""},
  {"tekst": "Znałem kiedyś Chinkę w barze,"},
  {"tekst": "Co śpiewała piosnki sprośne,"},
  {"tekst": "Gdy kimono swe rozdziała,"},
  {"tekst": "Cycki miała skośne"},
  {"tekst": ""},
  {"tekst": "Pływał z nami raz szantymen,"},
  {"tekst": "śpiewał bardzo niskim basem,"},
  {"tekst": "W rękach zawsze miał gitarę,"},
  {"tekst": "Ster trzymał kutasem"},
  {"tekst": ""},
  {"tekst": "Kiedy mocny szkwalik przywiał,"},
  {"tekst": "Ster mu w jaja tak przywalił,"},
  {"tekst": "Już nie basem, a sopranem,"},
  {"tekst": "Panny w porcie bawił."},
  {"tekst": ""},
  {"tekst": "Gdy przy sterze dzisiaj siedzi,"},
  {"tekst": "Szanty sobie dalej śpiewa,"},
  {"tekst": "Bez akordów i gitary,"},
  {"tekst": "Tylko a'cappella."},
  {"tekst": ""},
  {"tekst": ""},
  {"tekst": "Grant Kapitan z żoną pływał,"},
  {"tekst": "Nie dopatrzył raz załogi,"},
  {"tekst": "Odtąd ma bachorów kupę,"},
  {"tekst": "A na głowie rogi."},
  {"tekst": ""},
  {"tekst": "Znałem kiedyś kurtyzanę,"},
  {"tekst": "Co się zwała Ruda Brona,"},
  {"tekst": "W pół godziny obskoczyła"},
  {"tekst": "Eskadrę Nelsona."},
  {"tekst": ""},
  {"tekst": "Była raz w Londynie kurwa"},
  {"tekst": "Tak w rzemiośle wyrobiona,"},
  {"tekst": "Że w dwie doby obskoczyła"},
  {"tekst": "Eskadrę Nelsona."},
  {"tekst": ""},
  {"tekst": "Żyła raz w Londynie dziwka,"},
  {"tekst": "Co ją zwali Krwawa Bronka,"},
  {"tekst": "Bo jak zaciskała uda,"},
  {"tekst": "Obcinała członka."},
  {"tekst": ""},
  {"tekst": "I żadnemu żeglarzowi"},
  {"tekst": "Nie udało się jej dosiąść,"},
  {"tekst": "Bo dostawał opatrunek,"},
  {"tekst": "A ona korkociąg."},
  {"tekst": ""},
  {"tekst": "Ale trafił się marynarz,"},
  {"tekst": "Mieszkał podobno w Poczdamie,"},
  {"tekst": "Co drewnianą swą protezą"},
  {"tekst": "Zrobił kuku damie."},
  {"tekst": ""},
  {"tekst": "Znałem raz murzynkę w Rio,"},
  {"tekst": "Co w miłości była śmiała,"},
  {"tekst": "Nie uwierzysz daję słowo,"},
  {"tekst": "Całkiem w poprzek miała."},
  {"tekst": ""},
  {"tekst": "Znałem kiedyś pannę śliczną."},
  {"tekst": "Maszty stawiać uwielbiała,"},
  {"tekst": "Chłopa z łajbą pomyliła,"},
  {"tekst": "Lecz nie żałowała."},
  {"tekst": ""},
  {"tekst": "Miała baba Mikołajka"},
  {"tekst": "Wciąż ciągnęła go za jajka,"},
  {"tekst": "Raz za jedno, raz za drugie,"},
  {"tekst": "Potem za to długie."},
  {"tekst": ""},
  {"tekst": "Znałem kiedyś marynarza,"},
  {"tekst": "Co miał pecha tak wielkiego,"},
  {"tekst": "Wsadził ptaszka między greting"},
  {"tekst": "I nie wyjął jego."},
  {"tekst": ""},
  {"tekst": "Znałem raz pewnego majtka,"},
  {"tekst": "Co miał oczy jak dwie cipy,"},
  {"tekst": "Złapał syfa w środku morza,"},
  {"tekst": "W dodatku od kipy."},
  {"tekst": ""},
  {"tekst": "A w połowie tego rejsu,"},
  {"tekst": "Majtek ów popełnił gafę"},
  {"tekst": "I z grotmasztu wpadł do wody"},
  {"tekst": "Jajami na rafę."},
  {"tekst": ""},
  {"tekst": "Pewien majtek miał dwie nogi,"},
  {"tekst": "Co się nie trzymały kupy,"},
  {"tekst": "Bo przed laty zbił majątek"},
  {"tekst": "Na dawaniu dupy."},
  {"tekst": ""},
  {"tekst": "Żyła w Gdańsku cnotka Zocha,"},
  {"tekst": "Z każdym chciałaby się kochać,"},
  {"tekst": "Lecz stalową cnotę miała,"},
  {"tekst": "Rzewnie więc płakała."},
  {"tekst": ""},
  {"tekst": "Zośka dzięki swym przymiotom,"},
  {"tekst": "Podpuszczalska była wielce,"},
  {"tekst": "Wielu więc miało złamane,"},
  {"tekst": "Niekoniecznie serce."},
  {"tekst": ""},
  {"tekst": "Larsen choć był harpunnikiem,"},
  {"tekst": "Nie mógł Zośce przebić cnoty,"},
  {"tekst": "Choć jednym rzutem harpuna,"},
  {"tekst": "topił trzy U-Booty."},
  {"tekst": ""},
  {"tekst": "Słuchaj rady młody majtku,"},
  {"tekst": "Strzeż się dziewcząt w Yokochamie,"},
  {"tekst": "Tam są gejsze takie szybkie,"},
  {"tekst": "Zgwałcą nim ci stanie."},
  {"tekst": ""},
  {"tekst": "Gdy kapitan zachorował,"},
  {"tekst": "Zrobiono mu lewatywę,"},
  {"tekst": "Wlano w niego galon wody,"},
  {"tekst": "Przez prezerwatywę."},
  {"tekst": ""},
  {"tekst": "Może biedak by wyzdrowiał,"},
  {"tekst": "Bo kuracja pierwsza klasa,"},
  {"tekst": "Ale kondom był dziurawy,"},
  {"tekst": "Dostał adidasa."},
  {"tekst": ""},
  {"tekst": "Mały Jasiu z brudnym pyskiem,"},
  {"tekst": "Na Darze Pomorza pływał,"},
  {"tekst": "A że krzywy miał interes,"},
  {"tekst": "Pysk se obsikiwał."},
  {"tekst": ""},
  {"tekst": "Kiedy smutno Ci na wachcie,"},
  {"tekst": "Chcesz rozerwać się troszeczkę,"},
  {"tekst": "Wkładasz granat między nogi"},
  {"tekst": "I ciągniesz zawleczkę,"},
  {"tekst": ""},
  {"tekst": "Pływał raz marynarz który"},
  {"tekst": "Nosił w spodniach same dziury"},
  {"tekst": "Było widać przez te dziury"},
  {"tekst": "To co znoszą kury"},
  {"tekst": ""},
  {"tekst": "Pij mój bracie, twoje zdrowie"},
  {"tekst": "Jutro ci się humor przyda"},
  {"tekst": "Spirytus ci nie zaszkodzi,"},
  {"tekst": "Sztorm idzie - wyrzygasz."},
  {"tekst": ""},
  {"tekst": "Kto chce, to niechaj słucha,"},
  {"tekst": "Kto nie chce, niech nie słucha,"},
  {"tekst": "Jak balsam są dla ucha"},
  {"tekst": "Morskie opowieści."},
  {"tekst": ""},
  {"tekst": "Od Falklandu-śmy płynęli,"},
  {"tekst": "Doskonale brała ryba,"},
  {"tekst": "Mogłeś wędką wtedy złapać"},
  {"tekst": "Nawet wieloryba"},
  {"tekst": ""},
  {"tekst": "Kiedy znudzą Ci się szanty,"},
  {"tekst": "I żegluga, i Mazury,"},
  {"tekst": "Olej twego kapitana,"},
  {"tekst": "I spierdalaj w góry."},
  {"tekst": ""},
  {"tekst": "Znałem kiedyś marynarza,"},
  {"tekst": "Kochał piwo, no i tańce,"},
  {"tekst": "Jak się odlał to wypełniał"},
  {"tekst": "Śluzę na Guziance."},
  {"tekst": ""},
  {"tekst": "Raz stanąłem w Mikołajkach,"},
  {"tekst": "Patrzę, a tu spod \"Pagaja\""},
  {"tekst": "Wychodzi stary marynarz"},
  {"tekst": "Bez lewego jaja."},
  {"tekst": ""},
  {"tekst": "W Mikołajkach żył raz żeglarz,"},
  {"tekst": "Zjadł grochówki talerz cały,"},
  {"tekst": "Potem pierdząc z rufy jachtu"},
  {"tekst": "Przepłynął kanały."},
  {"tekst": ""},
  {"tekst": "Do Giżycka dziś płyniemy,"},
  {"tekst": "Nieźle daje, szóstką wieje,"},
  {"tekst": "Jak tak dalej dobrze pójdzie,"},
  {"tekst": "Rozkurwimy keję."},
  {"tekst": ""},
  {"tekst": "Grant Kapitan z żoną pływał,"},
  {"tekst": "Nie dopatrzył raz załogi,"},
  {"tekst": "Odtąd ma bachorów kupę,"},
  {"tekst": "A na głowie rogi."},
  {"tekst": ""},
  {"tekst": "Była raz w Londynie kurwa"},
  {"tekst": "Tak w rzemiośle wyrobiona,"},
  {"tekst": "Że w dwie doby obskoczyła"},
  {"tekst": "Eskadrę Nelsona."},
  {"tekst": ""},
  {"tekst": "Żyła w Kołobrzegu dziwka,"},
  {"tekst": "Co ją zwali Krwawa Bronka,"},
  {"tekst": "Bo jak zaciskała uda,"},
  {"tekst": "Obcinała członka."},
  {"tekst": ""},
  {"tekst": "I żadnemu żeglarzowi"},
  {"tekst": "Nie udało się jej dosiąść,"},
  {"tekst": "Bo dostawał opatrunek,"},
  {"tekst": "A ona korkociąg."},
  {"tekst": ""},
  {"tekst": "Ale trafił się marynarz,"},
  {"tekst": "Mieszkał podobno w Poczdamie,"},
  {"tekst": "Co drewnianą swą protezą"},
  {"tekst": "Zrobił kuku damie."},
  {"tekst": ""},
  {"tekst": "W Amsterdamie była knajpa,"},
  {"tekst": "Która w herbie miała Gryfa,"},
  {"tekst": "Z której nikt nie wyszedł wcześniej,"},
  {"tekst": "Niż nie złapał syfa."},
  {"tekst": ""},
  {"tekst": "Eskimosi są weseli,"},
  {"tekst": "Myją moczem swoje żony,"},
  {"tekst": "Pędzą bimber z ryb popsutych"},
  {"tekst": "I zjadają wrony."},
  {"tekst": ""},
  {"tekst": "Grenlandczycy, lud gościnny,"},
  {"tekst": "Więc pracują gorączkowo,"},
  {"tekst": "Sprowadzają lód z Syberii,"},
  {"tekst": "Nie wiemy dla kogo."},
  {"tekst": ""},
  {"tekst": "Jak do Gdyni wracalismy,"},
  {"tekst": "Goła baba mi się śniła."},
  {"tekst": "Gdy się rano obudziłem,"},
  {"tekst": "Dziura w burcie była."},
  {"tekst": ""},
  {"tekst": "Na Yan Mayen wielka draka,"},
  {"tekst": "Opowiem, jak rzecz się miała,"},
  {"tekst": "Kiedy wzięto nas za desant,"},
  {"tekst": "Ludność się poddała."},
  {"tekst": ""},
  {"tekst": "Kiedy szliśmy przez Pacyfik,"},
  {"tekst": "Wiatr pozrywał wszystkie wanty,"},
  {"tekst": "Przytuliłem się do klopa"},
  {"tekst": "I śpiewałem szanty."},
  {"tekst": ""},
  {"tekst": "Kiedy szliśmy przez Pacyfik,"},
  {"tekst": "Była wtedy straszna flauta,"},
  {"tekst": "Wprost na łajbę nam się zjebał"},
  {"tekst": "Ruski kosmonauta."},
  {"tekst": ""},
  {"tekst": "Powiedziała mi dziewczyna"},
  {"tekst": "Żeby wodą wódkę popić."},
  {"tekst": "Ja jej na to: \"Idź do diabła,"},
  {"tekst": "Czy chcesz mnie utopić?\""},
  {"tekst": ""},
  {"tekst": "Znałem kiedyś pannę śliczną."},
  {"tekst": "Maszty stawiać uwielbiała,"},
  {"tekst": "Chłopa z łajbą pomyliła,"},
  {"tekst": "Lecz nie żałowała."},
  {"tekst": ""},
  {"tekst": "Pływał raz marynarz, który"},
  {"tekst": "Żywił się wyłącznie wódką,"},
  {"tekst": "Dawał wódkę małolatom"},
  {"tekst": "No i prostytutkom."},
  {"tekst": ""},
  {"tekst": "Znałem raz pewnego majtka,"},
  {"tekst": "Kto nie wierzy, niech się śmieje,"},
  {"tekst": "Co swym chujem podczas wzwodu"},
  {"tekst": "Mógł zastąpić reje."},
  {"tekst": ""},
  {"tekst": "Znałem kiedyś marynarza,"},
  {"tekst": "Co miał pecha tak wielkiego,"},
  {"tekst": "Wsadził ptaszka między greting"},
  {"tekst": "I nie wyjął jego."},
  {"tekst": ""},
  {"tekst": "Znałem raz pewnego majtka,"},
  {"tekst": "Co miał oczy jak dwie cipy,"},
  {"tekst": "Złapał syfa w środku morza,"},
  {"tekst": "W dodatku od kipy."},
  {"tekst": ""},
  {"tekst": "A w połowie tego rejsu,"},
  {"tekst": "Majtek ów popełnił gafę"},
  {"tekst": "I z grotmasztu wpadł do wody"},
  {"tekst": "Jajami na rafę."},
  {"tekst": ""},
  {"tekst": "Pewien majtek miał dwie nogi,"},
  {"tekst": "Co się nie trzymały kupy,"},
  {"tekst": "Bo przed laty zbił majątek"},
  {"tekst": "Na dawaniu dupy."},
  {"tekst": ""},
  {"tekst": "Pływał raz po morzu kucharz,"},
  {"tekst": "W rękach praktyk był Onana,"},
  {"tekst": "A załoga się dziwiła"},
  {"tekst": "Skąd w kawie śmietana."},
  {"tekst": ""},
  {"tekst": "Pływał raz marynarz, który"},
  {"tekst": "Chuja miał jak trzy armaty"},
  {"tekst": "I wytryskiem swej giwery"},
  {"tekst": "Zatapiał fregaty."},
  {"tekst": ""},
  {"tekst": "Znałem raz pewnego kuka,"},
  {"tekst": "Co nie dupczył przez rok cały"},
  {"tekst": "I jak wsadził rybie w dupę,"},
  {"tekst": "To jej wyszły gały."},
  {"tekst": ""},
  {"tekst": "W dawnych czasach na żaglowcach"},
  {"tekst": "Żyły kozy tresowane,"},
  {"tekst": "Mogły one Ci zastąpić"},
  {"tekst": "Każdą kurtyzanę."},
  {"tekst": ""},
  {"tekst": "A gdy koza szła do kotła,"},
  {"tekst": "Bo czasami tak się zdarza,"},
  {"tekst": "To wtedy załoga cała"},
  {"tekst": "Jebała kucharza."},
  {"tekst": ""},
  {"tekst": "Pewien majtek miał papugę"},
  {"tekst": "Najsłynniejszą w całym świecie,"},
  {"tekst": "No bo była okrętową"},
  {"tekst": "Mistrzynią w minecie."},
  {"tekst": ""},
  {"tekst": "Za usługi tej papugi"},
  {"tekst": "Majtek pobierał dolara,"},
  {"tekst": "Nic dziwnego, w długim rejsie"},
  {"tekst": "Wzbogacił się zaraz."},
  {"tekst": ""},
  {"tekst": "A dla kogo za papugę"},
  {"tekst": "Była to za duża kwota,"},
  {"tekst": "Mógł pożyczyć od bosmana"},
  {"tekst": "Szczerbatego kota."},
  {"tekst": ""},
  {"tekst": "Pływał raz marynarz młody,"},
  {"tekst": "Co go nazywali pszczółką,"},
  {"tekst": "Dupcył wszystko prócz zegara,"},
  {"tekst": "Chyba, że z kukułką."},
  {"tekst": ""},
  {"tekst": "Żyła raz papuga, która"},
  {"tekst": "Miała tę jedną zaletę,"},
  {"tekst": "Że jak żadna inna dziwka"},
  {"tekst": "Robiła minetę."},
  {"tekst": ""},
  {"tekst": "Był na morzach taki zwyczaj"},
  {"tekst": "Iż załoga na żaglowce,"},
  {"tekst": "Że nie mogła zabrać żony,"},
  {"tekst": "Zabierała owce."},
  {"tekst": ""},
  {"tekst": "Nasz kapitan - twarda sztuka,"},
  {"tekst": "Nikt go dzisiaj nie odszuka,"},
  {"tekst": "Ale w końcu się skupimy"},
  {"tekst": "I mu wpierdolimy..."},
  {"tekst": ""},
  {"tekst": "Była sobie kiedyś łódka,"},
  {"tekst": "Gdzie się ciągle lała wódka,"},
  {"tekst": "Opierdalał się tam sternik"},
  {"tekst": "- Czerwony Październik."},
  {"tekst": ""},
  {"tekst": "Tam przy burcie bosman pije,"},
  {"tekst": "konia przy tym sobie bije,"},
  {"tekst": "ale pić szybko nie może,"},
  {"tekst": "bo się zrzyga w morze."},
  {"tekst": ""},
  {"tekst": "Szczur lądowy - twarda sztuka,"},
  {"tekst": "Ciężko zabić go czymkolwiek,"},
  {"tekst": "Lecz gdy w morze miałby ruszyć,"},
  {"tekst": "Narobiłby w spodnie."},
  {"tekst": ""},
  {"tekst": "Statek z portu już wypływa,"},
  {"tekst": "Każdy w kącie ściska babę,"},
  {"tekst": "Smutny tylko jest Warszawiak,"},
  {"tekst": "On kocha Warszawę."},
  {"tekst": ""},
  {"tekst": "My jesteśmy Warszawiaki,"},
  {"tekst": "Co palymy kataryny,"},
  {"tekst": "Żagle stoją nam w łopocie,"},
  {"tekst": "My to pierdolymy."},
  {"tekst": ""},
  {"tekst": "Była sobie kiedyś łódka,"},
  {"tekst": "Gdzie się ciągle lała wódka,"},
  {"tekst": "Opierdalał się tam sternik -"},
  {"tekst": "\"Czerwony Październik\"."},
  {"tekst": ""},
  {"tekst": "Gdy do portu przybijemy,"},
  {"tekst": "Wszyscy się do knajpy pchają"},
  {"tekst": "I już po godzinie picia"},
  {"tekst": "Nogi wyciągają."},
  {"tekst": ""},
  {"tekst": "W knajpie \"Pod ponurą małpą\""},
  {"tekst": "Rządzi jedna z takim zadkiem,"},
  {"tekst": "Że niejeden już nie wiedział,"},
  {"tekst": "Co zrobić z uszatkiem."},
  {"tekst": ""},
  {"tekst": "Gdy kolejki nie dotrzymasz,"},
  {"tekst": "To z kompanią się pożegnaj."},
  {"tekst": "Widać, Bracie, żeś jest ceper,"},
  {"tekst": "Dupa, a nie żeglarz."},
  {"tekst": ""},
  {"tekst": "Hej, chwała Panu Bogu,"},
  {"tekst": "Hej, Panu Bogu chwała,"},
  {"tekst": "Hej, kościół się zawalił,"},
  {"tekst": "Tawerna ostała."},
  {"tekst": ""},
  {"tekst": "Był raz szyper kutra \"Brzytwa\","},
  {"tekst": "Jedna myśl go wciąż trapiła,"},
  {"tekst": "Bo on myślał, że ma trypra,"},
  {"tekst": "A to była kiła."},
  {"tekst": ""},
  {"tekst": "Popłynęła kiedyś z nami"},
  {"tekst": "Pewna dama dla ochoty,"},
  {"tekst": "Powróciła cała, zdrowa,"},
  {"tekst": "Ale już bez cnoty."},
  {"tekst": ""},
  {"tekst": ""},
  {"tekst": "Nasz Kapitan twarda sztuka,"},
  {"tekst": "Nikt go tutaj nie oszuka,"},
  {"tekst": "Ale w końcu się skupimy"},
  {"tekst": "I mu wpier...my."},
  {"tekst": ""},
  {"tekst": "Na fregacie nie ma zmiłuj,"},
  {"tekst": "Zapier...ać trza od rana,"},
  {"tekst": "A wieczorem polerować"},
  {"tekst": "Laskę Kapitana."},
  {"tekst": ""},
  {"tekst": "Bosman na gitarze grywa,"},
  {"tekst": "Idzie mu to całkiem klawo,"},
  {"tekst": "Czasem chwyty popierdoli,"},
  {"tekst": "Wszyscy biją brawo."},
  {"tekst": ""},
  {"tekst": "Sternik, stary pijanica,"},
  {"tekst": "Ciągle biega, wódki szuka,"},
  {"tekst": "Jeden dzień bez alkoholu"},
  {"tekst": "I wyzionie ducha."},
  {"tekst": ""},
  {"tekst": "Znałem raz księżniczkę, która"},
  {"tekst": "Cipkę miała tak malutką,"},
  {"tekst": "Że dawała tylko z tyłu"},
  {"tekst": "I to krasnoludkom."},
  {"tekst": ""},
  {"tekst": "Płynie sobie statek prosto,"},
  {"tekst": "A załoga rzyga ostro,"},
  {"tekst": "Kiedyś woził on banany,"},
  {"tekst": "A dziś zarzygany."},
  {"tekst": ""},
  {"tekst": "Był raz sobie sternik, który"},
  {"tekst": "Na silniku ciągle pływał,"},
  {"tekst": "A że halsów nie rozróżniał,"},
  {"tekst": "Żagli nie używał."},
  {"tekst": ""},
  {"tekst": "Jak pływałem z chłopakami,"},
  {"tekst": "Cały miesiąc się nie myli,"},
  {"tekst": "Gdy poszli do \"Tropicany\","},
  {"tekst": "To ich nie wpuścili."},
  {"tekst": ""},
  {"tekst": "Raz kapitan na żygaczu"},
  {"tekst": "Cały dzień przesiedział w sraczu."},
  {"tekst": "Że turyści się nudzili,"},
  {"tekst": "Żygacz podpalili."},
  {"tekst": ""},
  {"tekst": "Znów pływaliśmy wieczorem,"},
  {"tekst": "A tu patrol z inspektorem,"},
  {"tekst": "Światła lśnią, syreny słyszę -"},
  {"tekst": "Mandat za pięć dyszek. (50 zł)"},
  {"tekst": ""},
  {"tekst": "Kumpel gryzie już paznokcie,"},
  {"tekst": "Zęby chodzą niczym pilnik."},
  {"tekst": "Co jest? - szturcham kumpla łokciem."},
  {"tekst": "Mieli lepszy silnik!"},
  {"tekst": ""},
  {"tekst": "Stąd nauka płynie prosta:"},
  {"tekst": "Jeśli pływać chcesz wieczorem,"},
  {"tekst": "Wyczarteruj łajbę z ponad"},
  {"tekst": "Stukonnym motorem."},
  {"tekst": ""},
  {"tekst": "Zwrotka ta jest ku przestrodze"},
  {"tekst": "Tych, co Włocha chcą w załodze."},
  {"tekst": "Włosi zamiast śpiewać szanty"},
  {"tekst": "Haftują zza wanty."},
  {"tekst": ""},
  {"tekst": "Znacznie większa jest pociecha"},
  {"tekst": "Na jachcie z kucharza - Czecha."},
  {"tekst": "Choć podaje knedle z ciastem,"},
  {"tekst": "Jest śmiesznym balastem."},
  {"tekst": ""},
  {"tekst": "Była dziwka w Węgorzewie,"},
  {"tekst": "Co kochała się na drzewie."},
  {"tekst": "Pagaj z tego drzewa właśnie"},
  {"tekst": "Na pewno nie trzaśnie!"},
  {"tekst": ""},
  {"tekst": "Żywy fracht nam pożarł flarę;"},
  {"tekst": "Z zada czuć mu było siarę."},
  {"tekst": "Był to - w co nikt nie w uwierzy"},
  {"tekst": "- Żubr wprost z Białowieży."},
  {"tekst": ""},
  {"tekst": "Weź do ręki złoty trunek,"},
  {"tekst": "Polej go na takielunek."},
  {"tekst": "Żaglom co piwka dostały"},
  {"tekst": "Nie straszne są szkwały."},
  {"tekst": ""},
  {"tekst": "Każdy naród ma swą mowę,"},
  {"tekst": "Taką mają też żeglarze,"},
  {"tekst": "Jak bardzo ważna to sztuka,"},
  {"tekst": "Zaraz się okaże."},
  {"tekst": ""},
  {"tekst": "Świeży adept na żeglarza"},
  {"tekst": "Krzyknął do kursantki młodej,"},
  {"tekst": "- Hej, Maryśka, jeno w mig tam,"},
  {"tekst": "Puść się na dziobowej!"},
  {"tekst": ""},
  {"tekst": "A gorliwa Marysieńka"},
  {"tekst": "Do komendy wykonania,"},
  {"tekst": "Cumę ciągle dzierżąc w ręku,"},
  {"tekst": "Stoi bez ubrania."},
  {"tekst": ""},
  {"tekst": "Znałem kiedyś marynarza,"},
  {"tekst": "Był najlepszy zaraz po mnie,"},
  {"tekst": "Gdyśmy w Świnoujściu chlali,"},
  {"tekst": "Nasrał mi na spodnie."},
  {"tekst": ""},
  {"tekst": "Kiedy pływaliśmy razem,"},
  {"tekst": "Nie było nam równych prawie,"},
  {"tekst": "Aż do czasu, kiedy poznał"},
  {"tekst": "Dziewczę na zabawie."},
  {"tekst": ""},
  {"tekst": "Zaraz stracił humor cały"},
  {"tekst": "Wciąż wpatrzony w nią jak ciele,"},
  {"tekst": "A najgorsze, że zapomniał,"},
  {"tekst": "Co to przyjaciele."},
  {"tekst": ""},
  {"tekst": "Kiedy ciężko Ci na duszy,"},
  {"tekst": "Kiedy w gardle znów Cię suszy,"},
  {"tekst": "Walnij sobie przyjacielu"},
  {"tekst": "Dużą dawkę chmielu."},
  {"tekst": ""},
  {"tekst": "Hej, ha, nalejcie piwa,"},
  {"tekst": "Niech się wszystkim w głowach kiwa,"},
  {"tekst": "Hej, ha, nalejcie piwa,"},
  {"tekst": "Niech się w głowach kiwa."},
  {"tekst": ""},
  {"tekst": "Czy wesele, czy też pogrzeb,"},
  {"tekst": "W domu, pracy, nawet szkole,"},
  {"tekst": "Zdrowiej z kufla ściągać browar,"},
  {"tekst": "Niż doić jabola."},
  {"tekst": ""},
  {"tekst": "Każdy rano leczy kaca,"},
  {"tekst": "Każdy w kącie obiad zwraca,"},
  {"tekst": "W głowie szumi myśl leniwa,"},
  {"tekst": "Nigdy więcej piwa."},
  {"tekst": ""},
  {"tekst": "I gdy skończy się choroba,"},
  {"tekst": "Chociaż ciągle ciąży głowa,"},
  {"tekst": "Uparcie biegniesz do baru,"},
  {"tekst": "Zaczerpnąć z browaru."},
  {"tekst": ""},
  {"tekst": "Jedni jadą sobie w góry,"},
  {"tekst": "Drudzy jadą na Mazury,"},
  {"tekst": "A ja biorę swój Komarek,"},
  {"tekst": "Zapierdzielam na browarek."},
  {"tekst": ""},
  {"tekst": "Hej, ho, butelka piwa,"},
  {"tekst": "W czasie burzy jest osłodą,"},
  {"tekst": "Pijmy więc dużo piwa,"},
  {"tekst": "Z tą brzozową wodą."},
  {"tekst": ""},
  {"tekst": "Okocimskie czy Wareckie"},
  {"tekst": "Świętokrzyskie czy Żywieckie"},
  {"tekst": "Każde piwo, każde zdrowe"},
  {"tekst": "Jak na moją głowę"},
  {"tekst": ""},
  {"tekst": "Siedzi diabeł na odpuście,"},
  {"tekst": "Słychać - w kuflu piwo chluśnie,"},
  {"tekst": "Zstąpił anioł z nieba szczytu,"},
  {"tekst": "Lecz nie miał kredytu."},
  {"tekst": ""},
  {"tekst": "Kiedy w dawnych czasach żyli,"},
  {"tekst": "Dobre piwo już robili,"},
  {"tekst": "Pili piwo pradziadowie,"},
  {"tekst": "Będą pić synowie."},
  {"tekst": ""},
  {"tekst": "Hej-że-ho! Polejcie piwa,"},
  {"tekst": "Niech się wszystkim głowa kiwa."},
  {"tekst": "Hej-że-ho! Polejcie piwa,"},
  {"tekst": "Niech się głowa kiwa."},
  {"tekst": ""},
  {"tekst": "Pij więc chłopcze, pij na zdrowie,"},
  {"tekst": "Nie próbuj tracić kolejki,"},
  {"tekst": "No, bo jaki żeglarz w świecie,"},
  {"tekst": "Stroni od butelki?"},
  {"tekst": ""},
  {"tekst": "Hej, ha! Kolejkę nalej!"},
  {"tekst": "Hej, ha! Kielichy wznieśmy!"},
  {"tekst": "Po kolejnej setce czystej"},
  {"tekst": "Pływać nam się zechce!"},
  {"tekst": ""},
  {"tekst": "A gdy z sił już opadniemy,"},
  {"tekst": "Setkę znowu wypijemy"},
  {"tekst": "I od razu przyjdzie humor"},
  {"tekst": "Do picia na umór."},
  {"tekst": ""},
  {"tekst": "Gdyby ta kuracja kiedyś"},
  {"tekst": "Skutku w mig nam nie przyniosła,"},
  {"tekst": "Znaczy wódka była chrzczona,"},
  {"tekst": "Zmienić trzeba lokal."},
  {"tekst": ""},
  {"tekst": "A gdy siły nas opuszczą,"},
  {"tekst": "Każdy zaśnie pod pokładem,"},
  {"tekst": "Nie dobudzi nas kapitan,"},
  {"tekst": "Nawet samopałem."},
  {"tekst": ""},
  {"tekst": "Wyślesz żeglarza młodego,"},
  {"tekst": "Po kilwater do bosmana,"},
  {"tekst": "Już nie wróci, będzie szukał"},
  {"tekst": "Do samego rana."},
  {"tekst": ""},
  {"tekst": "W Węgorzewie mieszka dziewka,"},
  {"tekst": "Co każdemu się oddaje,"},
  {"tekst": "Z dołu Puszcza Amazońska,"},
  {"tekst": "Z góry Himalaje."},
  {"tekst": ""},
  {"tekst": "A jej siostra chodzi smutna,"},
  {"tekst": "Użyć też by sobie chciała,"},
  {"tekst": "Z góry Stepy Akermańskie,"},
  {"tekst": "A z dołu Sahara."},
  {"tekst": ""},
  {"tekst": "Była raz panienka, która"},
  {"tekst": "Chciała wskoczyć mi na prącie."},
  {"tekst": "Jak się mama dowiedziała,"},
  {"tekst": "Tydzień stała w kącie."},
  {"tekst": ""},
  {"tekst": "Hej, ho, Angelika,"},
  {"tekst": "Hej, ho, Angelika,"},
  {"tekst": "Hej, ho, Angelika,"},
  {"tekst": "Wskocz mi na konika!"},
  {"tekst": ""},
  {"tekst": "Gdy już mama karę zdjęła,"},
  {"tekst": "Macać znowu mnie zaczęła,"},
  {"tekst": "Wciąż pytając tak dla ściemy,"},
  {"tekst": "Co tam mam w kieszeni?"},
  {"tekst": ""},
  {"tekst": "Była sobie Pchła-Szachrajka,"},
  {"tekst": "Co mi chciała lizać jajka."},
  {"tekst": "Jak do gęby je wsadziła,"},
  {"tekst": "To się udusiła."},
  {"tekst": ""},
  {"tekst": "Znałem w pewnym porcie dziewkę,"},
  {"tekst": "Była kiedyś niezła laska,"},
  {"tekst": "Odkąd walec ją przejechał,"},
  {"tekst": "Jest jak decha płaska."},
  {"tekst": ""},
  {"tekst": "Kiedy miodek szumi w głowie,"},
  {"tekst": "Zbiera się nam na wyznania,"},
  {"tekst": "Jak to było na początku"},
  {"tekst": "Naszego pływania."},
  {"tekst": ""},
  {"tekst": "Wiosłowanie trudna sztuka,"},
  {"tekst": "Więc do pniaka uwiązali."},
  {"tekst": "Próbujemy drzewo wyrwać"},
  {"tekst": "Razem z korzeniami."},
  {"tekst": ""},
  {"tekst": "Gdy wiosłować już umiemy,"},
  {"tekst": "Nawet w miarę równo, składnie,"},
  {"tekst": "Trzeba żagle tak postawić"},
  {"tekst": "By nie spocząć na dnie."},
  {"tekst": ""},
  {"tekst": "Żagle białe już wciągnięte,"},
  {"tekst": "Mnóstwo było z tym zachodu,"},
  {"tekst": "Wreszcie stało się - płyniemy,"},
  {"tekst": "Lecz rufą do przodu."},
  {"tekst": ""},
  {"tekst": "Przy czwóreczce to DZ-ta"},
  {"tekst": "Jest łódeczką dla rajdowca,"},
  {"tekst": "Raz mieliśmy na bukszprycie"},
  {"tekst": "Głowę surfingowca."},
  {"tekst": ""},
  {"tekst": "Barka keją treningową,"},
  {"tekst": "Fakt pożałowania godny,"},
  {"tekst": "Gdy prędkości nie wytracisz,"},
  {"tekst": "Masz okręt podwodny."},
  {"tekst": ""},
  {"tekst": "Więc kursanci na manewrach"},
  {"tekst": "Mieli z faktem niezłą walkę,"},
  {"tekst": "Raz miast żagle poluzować"},
  {"tekst": "Przyjebali w barkę."},
  {"tekst": ""},
  {"tekst": "Płynie łódź moja wzburzonym morzem,"},
  {"tekst": "Brzegu nie widać, wiatr w żagle wieje."},
  {"tekst": "Inny by pewnie już stracił głowę"},
  {"tekst": "Ja się tylko śmieję:"},
  {"tekst": ""},
  {"tekst": "Pływał z nami pewien gościu,"},
  {"tekst": "Z prostszym rozumem od knagi,"},
  {"tekst": "Gdy się dorwał chłop do rumpla,"},
  {"tekst": "Kręcił rufo-sztagi."},
  {"tekst": ""},
  {"tekst": "Znałem pewnego żeglarza,"},
  {"tekst": "Pływaliśmy razem Tangiem,"},
  {"tekst": "Był tak silny, że na chuju"},
  {"tekst": "Umiał podnieść sztangę."},
  {"tekst": "Pływał raz marynarz, który"},
  {"tekst": "Walił spiryt z grubej rury,"},
  {"tekst": "Główka go też nie bolała,"},
  {"tekst": "Bo to był nasz FALA."},
  {"tekst": ""},
  {"tekst": "Ryży Czajnik, kiedy popił,"},
  {"tekst": "Robił bardzo głupie miny,"},
  {"tekst": "Czasem rzygał do kokpiku"},
  {"tekst": "I podpieprzał liny."},
  {"tekst": ""},
  {"tekst": "Przyszedł bosman do tawerny,"},
  {"tekst": "Piwo!!! wrzasnął gromkim głosem"},
  {"tekst": "I od razu dostał w zęby -"},
  {"tekst": "Nie powiedział \"proszę\"."},
  {"tekst": ""},
  {"tekst": "Szczur lądowy - twarda sztuka,"},
  {"tekst": "Ciężko zabić go czymkolwiek,"},
  {"tekst": "Lecz gdy w morze miałby ruszyć,"},
  {"tekst": "Narobiłby w spodnie."},
  {"tekst": ""},
  {"tekst": "Statek z portu już wypływa,"},
  {"tekst": "Każdy w kącie ściska babę,"},
  {"tekst": "Smutny tylko jest Warszawiak,"},
  {"tekst": "On kocha Warszawę."},
  {"tekst": ""},
  {"tekst": "My jesteśmy Warszawiaki,"},
  {"tekst": "Co palymy kataryny,"},
  {"tekst": "Żagle stoją nam w łopocie,"},
  {"tekst": "My to pierdolymy."},
  {"tekst": ""},
  {"tekst": "Gdy do portu przybijemy,"},
  {"tekst": "Wszyscy się do knajpy pchają,"},
  {"tekst": "I już po godzinie picia"},
  {"tekst": "Nogi wyciągają."},
  {"tekst": ""},
  {"tekst": "W knajpie \"Pod ponurą małpą\""},
  {"tekst": "Rządzi jedna z takim zadkiem,"},
  {"tekst": "Że niejeden już nie wiedział,"},
  {"tekst": "Co zrobić z uszatkiem."},
  {"tekst": ""},
  {"tekst": "Gdy kolejki nie dotrzymasz,"},
  {"tekst": "To z kompanią się pożegnaj."},
  {"tekst": "Widać, Bracie, żeś jest ceper,"},
  {"tekst": "Dupa, a nie żeglarz."},
  {"tekst": ""},
  {"tekst": "Kiedy rum zaszumi w głowie,"},
  {"tekst": "W knajpie ruda tańczy cizia,"},
  {"tekst": "Każdy chętnie zapomina,"},
  {"tekst": "Co go w dupę gryzie."},
  {"tekst": ""},
  {"tekst": "Popłynęła kiedyś z nami"},
  {"tekst": "Pewna dama dla ochoty,"},
  {"tekst": "Powróciła cała zdrowa,"},
  {"tekst": "Ale już bez cnoty."},
  {"tekst": ""},
  {"tekst": "Na fregacie nie ma zmiłuj,"},
  {"tekst": "Zapierdalać trza od rana,"},
  {"tekst": "A wieczorem polerować"},
  {"tekst": "Laskę Kapitana."},
  {"tekst": ""},
  {"tekst": "Bosman na gitarze grywa,"},
  {"tekst": "Idzie mu to całkiem klawo,"},
  {"tekst": "Czasem chwyty popierdoli,"},
  {"tekst": "Wszyscy biją brawo."},
  {"tekst": ""},
  {"tekst": "Sternik, stary pijanica,"},
  {"tekst": "Ciągle biega, wódki szuka,"},
  {"tekst": "Jeden dzień bez alkoholu"},
  {"tekst": "I wyzionie ducha."},
  {"tekst": ""},
  {"tekst": "Znałem raz księżniczkę, która"},
  {"tekst": "Cipkę miała tak malutką,"},
  {"tekst": "Że dawała tylko z tyłu"},
  {"tekst": "I to krasnoludkom."},
  {"tekst": ""},
  {"tekst": "Płynie sobie statek prosto,"},
  {"tekst": "A załoga rzyga ostro,"},
  {"tekst": "Kiedyś woził on banany,"},
  {"tekst": "A dziś zarzygany."},
  {"tekst": ""},
  {"tekst": "Znałem kiedyś kapitana,"},
  {"tekst": "Urodził się chyba w piekle,"},
  {"tekst": "Bo jak nie miał co wyruchać,"},
  {"tekst": "To wyruchał szeklę."},
  {"tekst": ""},
  {"tekst": "Każdy żeglarz wie od dziecka,"},
  {"tekst": "Co to \"Czysta\", co \"Bałtycka\","},
  {"tekst": "I już jako jędrny malec"},
  {"tekst": "Macza w wódzie palec."},
  {"tekst": ""},
  {"tekst": "Pływał kiedyś majtek jeden"},
  {"tekst": "Masochista-pederasta,"},
  {"tekst": "Swe klejnoty często prażył"},
  {"tekst": "W prodiżu do ciasta."},
  {"tekst": ""},
  {"tekst": "A, że właśnie na tym statku,"},
  {"tekst": "Był cholerny problem z cukrem,"},
  {"tekst": "Wszyscy ciągle się dziwili,"},
  {"tekst": "Skąd to ciasto z lukrem?"},
  {"tekst": ""},
  {"tekst": "Gdy w żołądku tłuką fale"},
  {"tekst": "I chęć życia znika wszelka,"},
  {"tekst": "Nie trać bracie animuszu -"},
  {"tekst": "Jest jeszcze butelka!"},
  {"tekst": ""},
  {"tekst": "Komu się białe myszki nie śnią,"},
  {"tekst": "Ten za życia leży w dole,"},
  {"tekst": "My popłyńmy z naszą pieśnią"},
  {"tekst": "Poprzez monopole."},
  {"tekst": ""},
  {"tekst": "Źle w łódeczce jest baryłce,"},
  {"tekst": "Źle w łódeczce jest wódeczce."},
  {"tekst": "Chcecie wiedzieć, gdzie jej dobrze?"},
  {"tekst": "Wlejcie mi szklaneczkę!"},
  {"tekst": ""},
  {"tekst": "Kiedy nic Ci nie wychodzi,"},
  {"tekst": "Kiedy tęskni się do mamy,"},
  {"tekst": "Ktoś nam rzuca hasło: \"Nalej!\""},
  {"tekst": "I się zalewamy."},
  {"tekst": ""},
  {"tekst": "A na widok iceberga"},
  {"tekst": "Każde ciało drży w kożuchu,"},
  {"tekst": "Jaś Pobożny śpiewa psalmy,"},
  {"tekst": "A my - po maluchu!"},
  {"tekst": ""},
  {"tekst": "Jeśli myślisz, że piosenka"},
  {"tekst": "Trochę się nie trzyma kupy,"},
  {"tekst": "To układaj własne zwrotki,"},
  {"tekst": "Nie zawracaj dupy."},
  {"tekst": ""},
  {"tekst": "Kumpel nazwać swoją łajbę"},
  {"tekst": "Chciał tytułem jakiejś pieśni,"},
  {"tekst": "Ja mu na to - daj jej imię"},
  {"tekst": "\"Morskie Opowieści\"."},
  {"tekst": ""},
  {"tekst": "Był raz sobie sternik, który"},
  {"tekst": "Na silniku ciągle pływał,"},
  {"tekst": "A że halsów nie rozróżniał,"},
  {"tekst": "Żagli nie używał."},
  {"tekst": ""},
  {"tekst": "Jak pływałem z chłopakami,"},
  {"tekst": "Cały miesiąc się nie myli,"},
  {"tekst": "Gdy poszli do \"Tropicany\","},
  {"tekst": "To ich nie wpuścili."},
  {"tekst": ""},
  {"tekst": "Raz kapitan na żygaczu"},
  {"tekst": "Cały dzień przesiedział w sraczu."},
  {"tekst": "Że turyści się nudzili,"},
  {"tekst": "Żygacz podpalili."},
  {"tekst": ""},
  {"tekst": "ps. Żygacz, żygadło - jest to dość popularne wśród żeglarzy"},
  {"tekst": "określenie jednostki pływającej \"Ż\"eglugi Mazurskiej. :-)))"},
  {"tekst": ""},
  {"tekst": "Każdy naród ma swą mowę,"},
  {"tekst": "Taką mają też żeglarze,"},
  {"tekst": "Jak bardzo ważna to sztuka,"},
  {"tekst": "Zaraz się okaże."},
  {"tekst": ""},
  {"tekst": "Świeży adept na żeglarza"},
  {"tekst": "Krzyknął do kursantki młodej,"},
  {"tekst": "- Hej, Maryśka, jeno w mig tam,"},
  {"tekst": "Puść się na dziobowej!"},
  {"tekst": ""},
  {"tekst": "A gorliwa Marysieńka"},
  {"tekst": "Do komendy wykonania,"},
  {"tekst": "Cumę ciągle dzierżąc w ręku,"},
  {"tekst": "Stoi bez ubrania."},
  {"tekst": ""},
  {"tekst": "Zgraja tłoczy się przy barze,"},
  {"tekst": "Śmierdzi potem knajpa cała,"},
  {"tekst": "Piękna Lola weszła nagle,"},
  {"tekst": "Zgraja zawołała."},
  {"tekst": ""},
  {"tekst": "Kiedy w rejs znowu wypłynę,"},
  {"tekst": "Miej w pamięci wspólne chwile,"},
  {"tekst": "Walkę będę z sobą toczył"},
  {"tekst": "I o swoje życie."},
  {"tekst": ""},
  {"tekst": "Hej, bracie, wódki polej,"},
  {"tekst": "Niech mi gardło znowu pieści,"},
  {"tekst": "Taka jest życiowa kolej"},
  {"tekst": "Morskich Opowieści."},
  {"tekst": ""},
  {"tekst": "Piwko w barze się skończyło,"},
  {"tekst": "I już nie ma kogo pieścić,"},
  {"tekst": "Zanuć sobie do poduszki"},
  {"tekst": "Morskie Opowieści."},
  {"tekst": ""},
  {"tekst": "Kiedy pływaliśmy razem,"},
  {"tekst": "Nie było nam równych prawie,"},
  {"tekst": "Aż do czasu, kiedy poznał"},
  {"tekst": "Dziewczę na zabawie."},
  {"tekst": ""},
  {"tekst": "Zaraz stracił humor cały"},
  {"tekst": "Wciąż wpatrzony w nią jak ciele,"},
  {"tekst": "A najgorsze, że zapomniał,"},
  {"tekst": "Co to przyjaciele."},
  {"tekst": ""},
  {"tekst": "Tak to człeku w życiu bywa,"},
  {"tekst": "Gdy Ci baba na łeb wlezie,"},
  {"tekst": "Jak Cię wciśnie pod pantofel,"},
  {"tekst": "To tak, jakbyś nie żył."},
  {"tekst": ""},
  {"tekst": "W wokółziemski rejs ruszałem,"},
  {"tekst": "Było w mediach dużo krzyku,"},
  {"tekst": "Ale zawsze dopływałem"},
  {"tekst": "Do knajpy w... Szczedrzyku!"},
  {"tekst": ""},
  {"tekst": "W wokółziemski rejs ruszałem"},
  {"tekst": "Marząc o niejednym porcie,"},
  {"tekst": "Ale zawsze dryfowałem"},
  {"tekst": "Do \"Zęzy\" w Sztynorcie."},
  {"tekst": ""},
  {"tekst": "Choć dmuchało tylko \"cztery\","},
  {"tekst": "Jechaliśmy wciąż \"na kancie\","},
  {"tekst": "Bo stawiałem genakera"},
  {"tekst": "Na własnym palancie!"},
  {"tekst": ""},
  {"tekst": "Gdy nam dno przebiła rafa"},
  {"tekst": "I nasz szyper wpadł w panikę,"},
  {"tekst": "Wtedy dziurę kuk załatał"},
  {"tekst": "Świeżym naleśnikiem."},
  {"tekst": ""},
  {"tekst": "Gdy motorek diabli wzięli,"},
  {"tekst": "W sztormie poszły wszystkie szmaty,"},
  {"tekst": "To za spinakera robił"},
  {"tekst": "Biustonosz Agaty."},
  {"tekst": ""},
  {"tekst": "Kiedy flauta nas dorwała,"},
  {"tekst": "Osuszono wszystkie flaszki,"},
  {"tekst": "Kuk w kambuzie czynił zacier"},
  {"tekst": "Na bal kapitański."},
  {"tekst": ""},
  {"tekst": "Rok zmagałem się z żaglami,"},
  {"tekst": "By cumować w Ameryce,"},
  {"tekst": "Ale, kurwa, zapomniałem"},
  {"tekst": "Wyciągnąć kotwicę!"},
  {"tekst": ""},
  {"tekst": "Kiedy ciężko Ci na duszy,"},
  {"tekst": "Kiedy w gardle znów Cię suszy,"},
  {"tekst": "Walnij sobie przyjacielu"},
  {"tekst": "Dużą dawkę chmielu."},
  {"tekst": ""},
  {"tekst": "Hej, ha, nalejcie piwa,"},
  {"tekst": "Niech się wszystkim w głowach kiwa,"},
  {"tekst": "Hej, ha, nalejcie piwa,"},
  {"tekst": "Niech się w głowach kiwa."},
  {"tekst": ""},
  {"tekst": "Żadna kurwa, żadna dziwka"},
  {"tekst": "Nie zastąpi kufla piwka,"},
  {"tekst": "Kto nie wierzy niech spróbuje,"},
  {"tekst": "Jak piwo smakuje."},
  {"tekst": ""},
  {"tekst": "Gdyby nawet jakaś lala"},
  {"tekst": "Była lepsza od Specjala,"},
  {"tekst": "Zaraz Cię obejmie trwoga,"},
  {"tekst": "Jaka ona droga."},
  {"tekst": ""},
  {"tekst": "Czy wesele, czy też pogrzeb,"},
  {"tekst": "W domu, pracy, nawet szkole,"},
  {"tekst": "Zdrowiej z kufla ściągać browar,"},
  {"tekst": "Niż doić jabole."},
  {"tekst": ""},
  {"tekst": "Gdy siedzimy sobie w \"Dobrej\","},
  {"tekst": "Aga piwka nam podrzuca,"},
  {"tekst": "Kiedy chcemy zagrać w karty,"},
  {"tekst": "Ona nimi rzuca."},
  {"tekst": ""},
  {"tekst": "Gdy odurzą nas promile,"},
  {"tekst": "Film ma urwać się za chwilę,"},
  {"tekst": "Nikt dziś spojrzeć nie omieszka,"},
  {"tekst": "Gdzie stoi Agnieszka."},
  {"tekst": ""},
  {"tekst": "Każdy rano leczy kaca,"},
  {"tekst": "Każdy w kącie obiad zwraca,"},
  {"tekst": "W głowie szumi myśl leniwa,"},
  {"tekst": "Nigdy więcej piwa."},
  {"tekst": ""},
  {"tekst": "Dziś opowiem wam historię"},
  {"tekst": "Co zdarzyła się gdzieś w Rio"},
  {"tekst": "Bosman wódki nie chciał wypić"},
  {"tekst": "No i dostał w ryjo."},
  {"tekst": ""},
  {"tekst": "A że dzielnie się odgryzał"},
  {"tekst": "Cała gawiedź podkurwiona"},
  {"tekst": "Potem tylko wyszło na jaw"},
  {"tekst": "Wódka była chrzczona."},
  {"tekst": ""},
  {"tekst": "Bosman twarde jest chłopisko"},
  {"tekst": "Lepiej w drogę mu nie wchodzić"},
  {"tekst": "Pięciu gości już wynieśli"},
  {"tekst": "Szósty ledwie chodzi."},
  {"tekst": ""},
  {"tekst": "Barman co tę wódkę dawał"},
  {"tekst": "Długo biedak już nie pożył"},
  {"tekst": "Bo gdy bosman go zobaczył"},
  {"tekst": "W jaja mu przyłożył."},
  {"tekst": ""},
  {"tekst": "Po tej wielkiej bijatyce"},
  {"tekst": "Bosman w całym Rio znany"},
  {"tekst": "Tłum się kłębi dookoła"},
  {"tekst": "On jest podziwiany."},
  {"tekst": ""},
  {"tekst": "Wszystkie dziwki są już jego"},
  {"tekst": "Każda darmo da swe ciało"},
  {"tekst": "Zrobią tu dla niego wszystko"},
  {"tekst": "Byle mu się chciało."},
  {"tekst": ""},
  {"tekst": "Każda chce by ją przeleciał"},
  {"tekst": "A on wie jak im dogodzić"},
  {"tekst": "Bo po jego wizytacji"},
  {"tekst": "Wciąż nie mogą chodzić."},
  {"tekst": ""},
  {"tekst": "Dzisiaj bosman uśmiechnięty"},
  {"tekst": "Znowu wódki się napije"},
  {"tekst": "Nikt mu w Rio nie podskoczy"},
  {"tekst": "Bo wtedy nie żyje."},
  {"tekst": ""},
  {"tekst": "Potem im zaśpiewał szantę"},
  {"tekst": "Znaną prawie w całym świecie"},
  {"tekst": "No a jaki był jej refren"},
  {"tekst": "Chyba sami wiecie."},
  {"tekst": ""},
  {"tekst": "Pływał z nami jeden majtek,"},
  {"tekst": "Co go nazywali Kajtek,"},
  {"tekst": "Dziś załoga przerażona,"},
  {"tekst": "Bo to była ona."},
  {"tekst": ""},
  {"tekst": "Tylko bosman o tym wiedział,"},
  {"tekst": "Nic nikomu nie powiedział,"},
  {"tekst": "Za to dupczył ją zawzięcie,"},
  {"tekst": "Takie miał zajęcie."},
  {"tekst": ""},
  {"tekst": "W Mikołajkach żył raz żeglarz,"},
  {"tekst": "Zjadł grochówki talerz cały,"},
  {"tekst": "Potem pierdząc z rufy jachtu"},
  {"tekst": "Przepłynął kanały."},
  {"tekst": ""},
  {"tekst": "Do Giżycka dziś płyniemy,"},
  {"tekst": "Nieźle daje, szóstką wieje,"},
  {"tekst": "Jak tak dalej dobrze pójdzie,"},
  {"tekst": "Rozjebiemy keję."},
  {"tekst": ""},
  {"tekst": "W Amsterdamie była knajpa,"},
  {"tekst": "Która w herbie miała Gryfa,"},
  {"tekst": "Z której nikt nie wyszedł wcześniej,"},
  {"tekst": "Niż nie złapał syfa."},
  {"tekst": ""},
  {"tekst": "Eskimosi są weseli,"},
  {"tekst": "Myją moczem swoje żony,"},
  {"tekst": "Pędzą bimber z ryb popsutych"},
  {"tekst": "I zjadają wrony."},
  {"tekst": ""},
  {"tekst": "Grenlandczycy, lud gościnny,"},
  {"tekst": "Więc pracują gorączkowo,"},
  {"tekst": "Sprowadzają lód z Syberii,"},
  {"tekst": "Nie wiemy dla kogo."},
  {"tekst": ""},
  {"tekst": "Do Falklandu'śmy płynęli,"},
  {"tekst": "Goła baba mi się śniła."},
  {"tekst": "Gdy się rano obudziłem,"},
  {"tekst": "Dziura w burcie była."},
  {"tekst": ""},
  {"tekst": "Na Yan Mayen wielka draka,"},
  {"tekst": "Opowiem, jak rzecz się miała,"},
  {"tekst": "Kiedy wzięto nas za desant,"},
  {"tekst": "Ludność się poddała."},
  {"tekst": ""},
  {"tekst": "Powiedziała mi dziewczyna"},
  {"tekst": "Żeby wodą wódkę popić."},
  {"tekst": "Ja jej na to: \"Idź do diabła,"},
  {"tekst": "Czy chcesz mnie utopić?\""},
  {"tekst": ""},
  {"tekst": "I gdy skończy się choroba,"},
  {"tekst": "Chociaż ciągle ciąży głowa,"},
  {"tekst": "Uparcie biegniesz do baru,"},
  {"tekst": "Zaczerpnąć z browaru."},
  {"tekst": ""},
  {"tekst": "Pływał raz po morzu kucharz,"},
  {"tekst": "W rękach praktyk był Onana,"},
  {"tekst": "A załoga się dziwiła"},
  {"tekst": "Skąd w kawie śmietana."},
  {"tekst": ""},
  {"tekst": "Znałem pewnego kuchcika,"},
  {"tekst": "Co mu rumpel w dupie znika"},
  {"tekst": "I jak przyszła większa fala,"},
  {"tekst": "Oberwała jaja"},
  {"tekst": ""},
  {"tekst": "Pływał raz marynarz młody,"},
  {"tekst": "Co go nazywali pszczółką,"},
  {"tekst": "Dupcył wszystko prócz zegara,"},
  {"tekst": "Chyba, że z kukułką."},
  {"tekst": ""},
  {"tekst": "Kuchnia nasza jest wspaniała,"},
  {"tekst": "Czterech już do morza wnieśli,"},
  {"tekst": "Pozostałych zaś latryna"},
  {"tekst": "Nie może pomieścić."},
  {"tekst": ""},
  {"tekst": "Była sobie panna Ola"},
  {"tekst": "co nie miała na jabola"},
  {"tekst": "a że stara to cwaniara"},
  {"tekst": "Kupiła browara"},
  {"tekst": ""},
  {"tekst": "Okocimskie czy Wareckie"},
  {"tekst": "Świętokrzyskie czy Żywieckie"},
  {"tekst": "Każde piwo, każde zdrowe"},
  {"tekst": "Jak na moją głowę"},
  {"tekst": ""},
  {"tekst": "Kiedy w dawnych czasach żyli,"},
  {"tekst": "Dobre piwo już robili,"},
  {"tekst": "Pili piwo pradziadowie,"},
  {"tekst": "Będą pić synowie."},
  {"tekst": ""},
  {"tekst": "Hej-że-ho! Polejcie piwa,"},
  {"tekst": "Niech się wszystkim głowa kiwa."},
  {"tekst": "Hej-że-ho! Polejcie piwa,"},
  {"tekst": "Niech się głowa kiwa."},
  {"tekst": ""},
  {"tekst": "Pij więc chłopcze, pij na zdrowie,"},
  {"tekst": "Nie próbuj tracić kolejki,"},
  {"tekst": "No, bo jaki żeglarz w świecie,"},
  {"tekst": "Stroni od butelki?"},
  {"tekst": ""},
  {"tekst": "Hej, ha! Kolejkę nalej!"},
  {"tekst": "Hej, ha! Kielichy wznieśmy!"},
  {"tekst": "Po kolejnej setce czystej"},
  {"tekst": "Pływać nam się zechce!"},
  {"tekst": ""},
  {"tekst": "Znałem kiedyś dziewczę z Mazur,"},
  {"tekst": "Kochać bardzo się lubiła,"},
  {"tekst": "Gdy z góralem się przespała,"},
  {"tekst": "Zawału dostała."},
  {"tekst": ""},
  {"tekst": "Jedna dziewka była szybka,"},
  {"tekst": "Marynarzy pocieszała,"},
  {"tekst": "Jednak po szklaneczce whisky"},
  {"tekst": "Zaraz zasypiała."},
  {"tekst": ""},
  {"tekst": "Była w jednym porcie dziewka,"},
  {"tekst": "Co każdemu siebie dała,"},
  {"tekst": "Lecz ostatnio nie jest chętna,"},
  {"tekst": "Bo się zakochała."},
  {"tekst": ""},
  {"tekst": "Hej, ha! Wypijmy piwa!"},
  {"tekst": "Hej, ha! Wypijmy piwa!"},
  {"tekst": "Jak po tym browarze w słońcu"},
  {"tekst": "Dobrze nam się pływa!"},
  {"tekst": ""},
  {"tekst": "Kormorany tam latały,"},
  {"tekst": "Z drzew już liście pospadały,"},
  {"tekst": "Od ptasiego gówna puszki"},
  {"tekst": "Z piwem pordzewiały."},
  {"tekst": ""},
  {"tekst": "Do Giżycka chcemy wracać,"},
  {"tekst": "Silnik sprawnie zapalamy,"},
  {"tekst": "Przywaliła się straż wodna:"},
  {"tekst": "Ciszę zakłócamy."},
  {"tekst": ""},
  {"tekst": "Na pagajach więc płyniemy,"},
  {"tekst": "Żagle przehandlowaliśmy,"},
  {"tekst": "Chociaż sternik pierdział ostro,"},
  {"tekst": "Nie przyspieszaliśmy."},
  {"tekst": ""},
  {"tekst": "Jachtem naszym była Daisy,"},
  {"tekst": "Po morzach pływała nieraz,"},
  {"tekst": "Na Mazurach wał z niej wypadł,"},
  {"tekst": "Poszła na dno zaraz."},
  {"tekst": ""},
  {"tekst": "Załoga niedoświadczona"},
  {"tekst": "Myślała, że to fontanna,"},
  {"tekst": "A to tylko statek tonął"},
  {"tekst": "Na środku Kisajna."},
  {"tekst": ""},
  {"tekst": "Gdy kolejki nie dotrzymasz,"},
  {"tekst": "To z kompanią się pożegnaj."},
  {"tekst": "Widać, Bracie, żeś jest ceper,"},
  {"tekst": "Dupa, a nie żeglarz."},
  {"tekst": ""},
  {"tekst": "Nasz Kapitan twarda sztuka,"},
  {"tekst": "Nikt go tutaj nie oszuka,"},
  {"tekst": "Ale w końcu się skupimy"},
  {"tekst": "I mu wpierdolimy."},
  {"tekst": ""},
  {"tekst": "Na fregacie nie ma zmiłuj,"},
  {"tekst": "Zapierdalać trza od rana,"},
  {"tekst": "A wieczorem polerować"},
  {"tekst": "Laskę Kapitana."},
  {"tekst": ""},
  {"tekst": "Bosman na gitarze grywa,"},
  {"tekst": "Idzie mu to całkiem klawo,"},
  {"tekst": "Czasem chwyty popierdoli,"},
  {"tekst": "Wszyscy biją brawo."},
  {"tekst": ""},
  {"tekst": "Sternik, stary pijanica,"},
  {"tekst": "Ciągle biega, wódki szuka,"},
  {"tekst": "Jeden dzień bez alkoholu"},
  {"tekst": "I wyzionie ducha."},
  {"tekst": ""},
  {"tekst": "Płynie sobie statek prosto,"},
  {"tekst": "A załoga rzyga ostro,"},
  {"tekst": "Kiedyś woził on banany,"},
  {"tekst": "A dziś zarzygany."},
  {"tekst": ""},
  {"tekst": "Znałem kiedyś kapitana,"},
  {"tekst": "Urodził się chyba w piekle,"},
  {"tekst": "Bo jak nie miał co wyruchać,"},
  {"tekst": "To wyruchał szeklę."},
  {"tekst": ""},
  {"tekst": "Kuchnia nasza jest wspaniała,"},
  {"tekst": "Czterech już do morza wnieśli,"},
  {"tekst": "Pozostałych zaś latryna"},
  {"tekst": "Nie może pomieścić."},
  {"tekst": ""},
  {"tekst": "Pływał raz marynarz, który"},
  {"tekst": "Walił spiryt z grubej rury,"},
  {"tekst": "Główka go nic nie bolała,"},
  {"tekst": "Bo to był nasz FALA."},
  {"tekst": ""},
  {"tekst": "Ryży Czajnik, kiedy popił,"},
  {"tekst": "Robił bardzo głupie miny,"},
  {"tekst": "Czasem rzygał do kokpiku"},
  {"tekst": "I podpieprzał liny."},
  {"tekst": ""},
  {"tekst": "Dziś w Giżycku jakieś szanty,"},
  {"tekst": "Twierdza Boyen oblężona,"},
  {"tekst": "Takich tłumów nie widziano"},
  {"tekst": "Od czasów lugola."},
  {"tekst": ""},
  {"tekst": "Mocz się leje, browar leci,"},
  {"tekst": "Pewnie zrobią nowe dzieci,"},
  {"tekst": "Niech rosną młodzi żeglarze,"},
  {"tekst": "Życie im pokaże."},
  {"tekst": ""},
  {"tekst": "Browar płynie, mocz się leje,"},
  {"tekst": "Parka spieprza w jakieś knieje,"},
  {"tekst": "Pewnie zrobią nowe dziecię -"},
  {"tekst": "Dużo nas na świecie!"},
  {"tekst": ""},
  {"tekst": "Za lat naście się spotkamy,"},
  {"tekst": "Przy browarku pogadamy,"},
  {"tekst": "Niech rosną młodzi żeglarze,"},
  {"tekst": "Życie im pokaże."},
  {"tekst": ""},
  {"tekst": "Będą pływać bez patentu,"},
  {"tekst": "Bo w Warszawie ktoś dał siana,"},
  {"tekst": "Pewnie wpieprzą się na keję,"},
  {"tekst": "Zabiją bosmana."},
  {"tekst": ""},
  {"tekst": "Wyślesz żeglarza młodego,"},
  {"tekst": "Po kilwater do bosmana,"},
  {"tekst": "Już nie wróci, będzie szukał"},
  {"tekst": "Do samego rana."},
  {"tekst": ""},
  {"tekst": "Była raz panienka, która"},
  {"tekst": "Chciała wskoczyć mi na prącie."},
  {"tekst": "Jak się mama dowiedziała,"},
  {"tekst": "Tydzień stała w kącie."},
  {"tekst": ""},
  {"tekst": "Gdy już mama karę zdjęła,"},
  {"tekst": "Macać znowu mnie zaczęła,"},
  {"tekst": "Wciąż pytając tak dla ściemy,"},
  {"tekst": "Co tam mam w kieszeni?"},
  {"tekst": ""},
  {"tekst": "Znałem pewnego żeglarza,"},
  {"tekst": "Pływaliśmy razem Tangiem,"},
  {"tekst": "Był tak silny, że na chuju"},
  {"tekst": "Umiał podnieść sztangę."},
  {"tekst": ""},
  {"tekst": "Gdy chciał wszystkim zaszpanować,"},
  {"tekst": "Rekord świata chyba pobił,"},
  {"tekst": "Jednak gdy mu kutas oklapł,"},
  {"tekst": "Dziurę w burcie zrobił."},
  {"tekst": ""},
  {"tekst": "Znałem w pewnym porcie dziewkę,"},
  {"tekst": "Była kiedyś niezła laska,"},
  {"tekst": "Odkąd walec ją przejechał,"},
  {"tekst": "Jest jak decha płaska."},
  {"tekst": ""},
  {"tekst": "Pływał z nami raz Kapitan -"},
  {"tekst": "Napalony transwestyta."},
  {"tekst": "Cała załoga wołała"},
  {"tekst": "Na niego Lolita."},
  {"tekst": ""},
  {"tekst": "Gdy rzuciła go dziewczyna"},
  {"tekst": "Postanowił się utopić,"},
  {"tekst": "Przywiązał do chuja kamień"},
  {"tekst": "I do morza wskoczył."},
  {"tekst": ""},
  {"tekst": "Nagle wyleciał jak z procy"},
  {"tekst": "I mu trochę zrzedła mina,"},
  {"tekst": "Krzyczał, że na horyzoncie"},
  {"tekst": "Zobaczył rekina."},
  {"tekst": ""},
  {"tekst": "\"O żesz kurwa!\"- klął bez przerwy -"},
  {"tekst": "\"Ale się najadłem strachu,"},
  {"tekst": "Nie można nawet spokojnie"},
  {"tekst": "Złożyć kości w piachu!\""},
  {"tekst": ""},
  {"tekst": "Znałem raz pewnego majtka,"},
  {"tekst": "Był troszeczkę nienormalny,"},
  {"tekst": "Bo uprawiał z wielorybem"},
  {"tekst": "W wodzie seks analny."},
  {"tekst": ""},
  {"tekst": "Kiedy miodek szumi w głowie,"},
  {"tekst": "Zbiera się nam na wyznania,"},
  {"tekst": "Jak to było na początku"},
  {"tekst": "Naszego pływania."},
  {"tekst": ""},
  {"tekst": "Wiosłowanie trudna sztuka,"},
  {"tekst": "Więc do pniaka uwiązali."},
  {"tekst": "Próbujemy drzewo wyrwać"},
  {"tekst": "Razem z korzeniami."},
  {"tekst": ""},
  {"tekst": "Gdy wiosłować już umiemy,"},
  {"tekst": "Nawet w miarę równo, składnie,"},
  {"tekst": "Trzeba żagle tak postawić"},
  {"tekst": "By nie spocząć na dnie."},
  {"tekst": ""},
  {"tekst": "Żagle białe już wciągnięte,"},
  {"tekst": "Mnóstwo było z tym zachodu,"},
  {"tekst": "Wreszcie stało się - płyniemy,"},
  {"tekst": "Lecz rufą do przodu."},
  {"tekst": ""},
  {"tekst": "Przy czwóreczce to DZ-ta"},
  {"tekst": "Jest łódeczką dla rajdowca,"},
  {"tekst": "Raz mieliśmy na bukszprycie"},
  {"tekst": "Głowę surfingowca."},
  {"tekst": ""},
  {"tekst": "Barka keją treningową,"},
  {"tekst": "Fakt pożałowania godny,"},
  {"tekst": "Gdy prędkości nie wytracisz,"},
  {"tekst": "Masz okręt podwodny."},
  {"tekst": ""},
  {"tekst": "Więc kursanci na manewrach"},
  {"tekst": "Mieli z faktem niezłą walkę,"},
  {"tekst": "Raz miast żagle poluzować"},
  {"tekst": "Przyjebali w barkę."},
  {"tekst": ""},
  {"tekst": "Pływał z nami pewien gościu,"},
  {"tekst": "Z prostszym rozumem od knagi,"},
  {"tekst": "Gdy się dorwał chłop do rumpla,"},
  {"tekst": "Kręcił rufo-sztagi."},
  {"tekst": ""},
  {"tekst": "Gdy zeszliśmy na nabrzeże,"},
  {"tekst": "W zapomnienie poszło morze,"},
  {"tekst": "Bo siedziało na polerze"},
  {"tekst": "Jakieś blond niebożę!"},
  {"tekst": ""},
  {"tekst": "Popękały wszystkie spodnie,"},
  {"tekst": "Kiedy na nasz widok wstała,"},
  {"tekst": "Potem całe dwa tygodnie"},
  {"tekst": "Sufit oglądała!"},
  {"tekst": ""},
  {"tekst": "Kiedy już odpływaliśmy,"},
  {"tekst": "Dla uciechy i dla sportu"},
  {"tekst": "Wcisnęliśmy do bakisty"},
  {"tekst": "Nasze dziewczę z portu."},
  {"tekst": ""},
  {"tekst": "Choć się fajnie żeglowało,"},
  {"tekst": "Każdy szukał wnet doktora,"},
  {"tekst": "Bo się kurwa okazało -"},
  {"tekst": "Mewka była chora."},
  {"tekst": ""},
  {"tekst": "W dzień trapiła ją gorączka,"},
  {"tekst": "W nocy ją swędziła cipa;"},
  {"tekst": "Pewnie była to rzeżączka,"},
  {"tekst": "No bo skąd by grypa?"},
  {"tekst": ""},
  {"tekst": "Tam, gdzie straszne wichry wieją,"},
  {"tekst": "Tam, gdzie wódki nie sprzedają,"},
  {"tekst": "Tylko najlepsi żeglarze"},
  {"tekst": "Strachu nie zaznają"},
  {"tekst": ""},
  {"tekst": "Stoi baca na przystani"},
  {"tekst": "I ogromnie się dziwuje,"},
  {"tekst": "Że wszyscy żeglarze mają"},
  {"tekst": "Takie wielkie chuje."},
  {"tekst": ""},
  {"tekst": "Coś na horyzoncie błyska,"},
  {"tekst": "Więc w przypływie euforii"},
  {"tekst": "\"Pierwszy\" wrzasnął, że to chyba"},
  {"tekst": "Brzegi Kalifornii!"},
  {"tekst": ""},
  {"tekst": "To nie brzegi Sacramento,"},
  {"tekst": "Ino polska wieś Chałupy,"},
  {"tekst": "A te błyski, to nie złoto,"},
  {"tekst": "Tylko gołe dupy!"},
  {"tekst": ""},
  {"tekst": "Gdy w beczce dno prześwieca"},
  {"tekst": "alkohol się zaleca,"},
  {"tekst": "pijmy więc pijmy chłopcy,"},
  {"tekst": "trunek nam nieobcy."},
  {"tekst": ""},
  {"tekst": "Gdy w żołądku tłuką fale"},
  {"tekst": "I chęć życia znika wszelka,"},
  {"tekst": "Nie trać bracie animuszu -"},
  {"tekst": "Jest jeszcze butelka!"},
  {"tekst": ""},
  {"tekst": "Komu białe myszki nie śnią,"},
  {"tekst": "Ten za życia leży w dole,"},
  {"tekst": "My popłyńmy z naszą pieśnią"},
  {"tekst": "Poprzez monopole."},
  {"tekst": ""},
  {"tekst": "Źle w łódeczce jest baryłce,"},
  {"tekst": "Źle w łódeczce jest wódeczce."},
  {"tekst": "Chcecie wiedzieć, gdzie jej dobrze?"},
  {"tekst": "Wlejcie mi szklaneczkę!"},
  {"tekst": ""},
  {"tekst": "Kiedy nic Ci nie wychodzi,"},
  {"tekst": "Kiedy tęskni się do mamy,"},
  {"tekst": "Ktoś nam rzuca hasło: \"Nalej!\""},
  {"tekst": "I się zalewamy."},
  {"tekst": ""},
  {"tekst": "A na widok iceberga"},
  {"tekst": "Każde ciało drży w kożuchu,"},
  {"tekst": "Jaś Pobożny śpiewa psalmy,"},
  {"tekst": "A my - po maluchu!"},
  {"tekst": ""},
  {"tekst": "Znałem kiedyś kapitana,"},
  {"tekst": "Urodził się chyba w piekle,"},
  {"tekst": "Bo jak nie miał co wyruchać,"},
  {"tekst": "To wyruchał szeklę."},
  {"tekst": ""},
  {"tekst": "Trzymaj mnie, bo będę rzygał,"},
  {"tekst": "Trzymaj mnie, bo będe rzygał,"},
  {"tekst": "Trzymaj mnie, bo będę rzygał,"},
  {"tekst": "Trzymaj mnie, bo rzygam!"},
  {"tekst": ""},
  {"tekst": "Każdy żeglarz wie od dziecka,"},
  {"tekst": "Co to \"Czysta\", co \"Bałtycka\","},
  {"tekst": "I już jako jędrny malec"},
  {"tekst": "Macza w wódzie palec."},
  {"tekst": ""},
  {"tekst": "Pływał kiedyś majtek jeden"},
  {"tekst": "Masochista-pederasta,"},
  {"tekst": "Swe klejnoty często prażył"},
  {"tekst": "W prodiżu do ciasta."},
  {"tekst": ""},
  {"tekst": "A, że właśnie na tym statku,"},
  {"tekst": "Był cholerny problem z cukrem,"},
  {"tekst": "Wszyscy ciągle się dziwili,"},
  {"tekst": "Skąd to ciasto z lukrem?"},
  {"tekst": ""},
  {"tekst": "Widzisz, biały szkwał się zbliża?"},
  {"tekst": "Zrzucaj szybko wszystkie szmaty"},
  {"tekst": "Jak nie zdążysz, to do Giża"},
  {"tekst": "Wpłyniesz przez zaświaty."},
  {"tekst": ""},
  {"tekst": "Zjeść co tanio w Mikołajkach?"},
  {"tekst": "Takiej knajpy się nie trafi!"},
  {"tekst": "Wszystkie dawno już są w rękach"},
  {"tekst": "Syryjczyków mafii."},
  {"tekst": ""},
  {"tekst": "W mej załodze był konował,"},
  {"tekst": "Co swe buty wciąż pucował,"},
  {"tekst": "Poza tym po czubek głowy"},
  {"tekst": "Strój miał adamowy."},
  {"tekst": ""},
  {"tekst": "Pływał z nami raz patałach;"},
  {"tekst": "Wnosił błoto na sandałach,"},
  {"tekst": "Po sztormie z niego zostały"},
  {"tekst": "Tylko te sandały"},
  {"tekst": ""},
  {"tekst": "Chociaż była martwa cisza,"},
  {"tekst": "W dzień z Ogonków aż do Pisza"},
  {"tekst": "Przeszliśmy - lecz gorzko płacząc,"},
  {"tekst": "Bo ciągle burłacząc."},
  {"tekst": ""},
  {"tekst": "W \"Zęzie\" znowu tłok jest wielki"},
  {"tekst": "I zabawa pierwsza klasa,"},
  {"tekst": "Ktoś kumplowi odpiął szelki,"},
  {"tekst": "Widać mu k...olana. ;-)"},
  {"tekst": ""},
  {"tekst": "Po Mazurach pływa człowiek,"},
  {"tekst": "Co się kryje własnym jachtem."},
  {"tekst": "On się kryje lat sześćdziesiąt"},
  {"tekst": "Ciągle przed Wermachtem."},
  {"tekst": ""},
  {"tekst": "Żreć będziecie dzisiaj z zęzy!"},
  {"tekst": "Krzyczę do załogi w porcie."},
  {"tekst": "Całe szczęście dla załogi"},
  {"tekst": "To było w Sztynorcie."},
  {"tekst": ""},
  {"tekst": "Kiedy znużysz się pływaniem"},
  {"tekst": "To śpiewaczka operowa"},
  {"tekst": "Rejs umili ci śpiewaniem"},
  {"tekst": "I lizaniem ro.....gówki. ;-)"},
  {"tekst": ""},
  {"tekst": "Kiedy znudzą ci się panny,"},
  {"tekst": "Dziwki, zdziry i niecnotki,"},
  {"tekst": "To do \"Morskich opowieści\""},
  {"tekst": "Dopisz nowe zwrotki!"},
  {"tekst": ""},
  {"tekst": "W carskiej Rosji był krążownik,"},
  {"tekst": "Załoga się wygłupiała:"},
  {"tekst": "Gdy kapitan głośno pierdnął,"},
  {"tekst": "To strzelano z działa."},
  {"tekst": ""},
  {"tekst": "I przypadkiem tak się stało,"},
  {"tekst": "Chociaż za to nie dam głowy,"},
  {"tekst": "Dali sygnał do ataku"},
  {"tekst": "Na Pałac Zimowy."},
  {"tekst": ""},
  {"tekst": "Kuk gotował grochóweczkę,"},
  {"tekst": "Bo nic więcej nie potrafił,"},
  {"tekst": "Z Aurory śmierdziało z deczkę,"},
  {"tekst": "A Rosję szlag trafił.."},
  {"tekst": ""},
  {"tekst": "Tak to człeku w życiu bywa,"},
  {"tekst": "Gdy Ci baba na łeb wlezie,"},
  {"tekst": "Jak Cię wciśnie pod pantofel,"},
  {"tekst": "To tak, jakbyś nie żył."},
  {"tekst": ""},
  {"tekst": "W wokółziemski rejs ruszałem,"},
  {"tekst": "Było w mediach dużo krzyku,"},
  {"tekst": "Ale zawsze dopływałem"},
  {"tekst": "Do knajpy w... Szczedrzyku!"},
  {"tekst": ""},
  {"tekst": "lub w zależności od akwenu:"},
  {"tekst": ""},
  {"tekst": "W wokółziemski rejs ruszałem"},
  {"tekst": "Marząc o niejednym porcie,"},
  {"tekst": "Ale zawsze dryfowałem"},
  {"tekst": "Do \"Zęzy\" w Sztynorcie."},
  {"tekst": ""},
  {"tekst": "Choć dmuchało tylko \"cztery\","},
  {"tekst": "Jechaliśmy wciąż \"na kancie\","},
  {"tekst": "Bo stawiałem genakera"},
  {"tekst": "Na własnym palancie!"},
  {"tekst": ""},
  {"tekst": "Gdy \"Starego\" zmyła fala,"},
  {"tekst": "Chief na sterze stał do rana,"},
  {"tekst": "A my wszyscy dmuchaliśmy"},
  {"tekst": "Babę kapitana."},
  {"tekst": ""},
  {"tekst": "Znałem kiedyś dziewczę z Mazur,"},
  {"tekst": "Kochać bardzo się lubiała,"},
  {"tekst": "Gdy z góralem się przespała,"},
  {"tekst": "Zawału dostała."},
  {"tekst": ""},
  {"tekst": "Jedna dziewka była szybka,"},
  {"tekst": "Marynarzy pocieszała,"},
  {"tekst": "Jednak po szklaneczce whisky"},
  {"tekst": "Zaraz zasypiała."},
  {"tekst": ""},
  {"tekst": "Była w jednym porcie dziewka,"},
  {"tekst": "Co każdemu siebie dała,"},
  {"tekst": "Lecz ostatnio nie jest chętna,"},
  {"tekst": "Bo się zakochała."},
  {"tekst": ""},
  {"tekst": "Gdy na Dobskim pływaliśmy,"},
  {"tekst": "To łódkę wyjeb...śmy,"},
  {"tekst": "Dotarliśmy wpław do wyspy,"},
  {"tekst": "Gównem dostaliśmy."},
  {"tekst": ""},
  {"tekst": "Hej, ha! Wypijmy piwa!"},
  {"tekst": "Hej, ha! Wypijmy piwa!"},
  {"tekst": "Jak po tym browarze w słońcu"},
  {"tekst": "Dobrze nam się pływa!"},
  {"tekst": ""},
  {"tekst": "Kormorany tam latały,"},
  {"tekst": "Z drzew już liście pospadały,"},
  {"tekst": "Od ptasiego gówna puszki"},
  {"tekst": "Z piwem pordzewiały."},
  {"tekst": ""},
  {"tekst": "Gdy do Doby dotarliśmy,"},
  {"tekst": "Piwa w sklepie już nie było,"},
  {"tekst": "Więc z tej dziury bardzo szybko"},
  {"tekst": "Trzeba nam odpłynąć."},
  {"tekst": ""},
  {"tekst": "Do Giżycka chcemy wracać,"},
  {"tekst": "Silnik sprawnie zapalamy,"},
  {"tekst": "Przywaliła się straż wodna:"},
  {"tekst": "Ciszę zakłócamy."},
  {"tekst": ""},
  {"tekst": "Na pagajach więc płyniemy,"},
  {"tekst": "Żagle przehandlowaliśmy,"},
  {"tekst": "Chociaż sternik pierdział ostro,"},
  {"tekst": "Nie przyspieszaliśmy."},
  {"tekst": ""},
  {"tekst": "Jachtem naszym była Daisy,"},
  {"tekst": "Po morzach pływała nieraz,"},
  {"tekst": "Na Mazurach wał z niej wypadł,"},
  {"tekst": "Poszła na dno zaraz."},
  {"tekst": ""},
  {"tekst": "Załoga niedoświadczona"},
  {"tekst": "Myślała, że to fontanna,"},
  {"tekst": "A to tylko statek tonął"},
  {"tekst": "Na środku Kisajna."},
  {"tekst": ""},
  {"tekst": "Więc nie pływaj nigdy jachtem,"},
  {"tekst": "Co na morzu przeżył życie,"},
  {"tekst": "Po małych polskich Mazurach -"},
  {"tekst": "Po co tracić życie."},
  {"tekst": ""},
  {"tekst": "Dziś w Giżycku jakieś szanty,"},
  {"tekst": "Twierdza Boyen oblężona,"},
  {"tekst": "Takich tłumów nie widziano"},
  {"tekst": "Od czasów lugola."},
  {"tekst": ""},
  {"tekst": "Mocz się leje, browar leci,"},
  {"tekst": "Pewnie zrobią nowe dzieci,"},
  {"tekst": "Niech rosną młodzi żeglarze,"},
  {"tekst": "Życie im pokaże."},
  {"tekst": ""},
  {"tekst": "Browar płynie, mocz się leje,"},
  {"tekst": "Parka spieprza w jakieś knieje,"},
  {"tekst": "Pewnie zrobią nowe dziecię -"},
  {"tekst": "Dużo nas na świecie!"},
  {"tekst": ""},
  {"tekst": "Za lat naście się spotkamy,"},
  {"tekst": "Przy browarku pogadamy,"},
  {"tekst": "Niech rosną młodzi żeglarze,"},
  {"tekst": "Życie im pokaże."},
  {"tekst": ""},
  {"tekst": "Będą pływać bez patentu,"},
  {"tekst": "Bo ktoś tam dał sobie siana,"},
  {"tekst": "Pewnie wpieprzą się na keję,"},
  {"tekst": "Zabiją bosmana."},
  {"tekst": ""},
  {"tekst": "Gdy do portu przybijemy,"},
  {"tekst": "Wszyscy się do knajpy pchają"},
  {"tekst": "I już po godzinie picia"},
  {"tekst": "Nogi wyciągają."},
  {"tekst": ""},
  {"tekst": "Wszedł raz bosman do kibelka,"},
  {"tekst": "A tam majtek jadł serdelka,"},
  {"tekst": "Bosman zlał się z niego równo,"},
  {"tekst": "Myślał, że to GÓWNO."},
  {"tekst": ""},
  {"tekst": "Kiedy szliśmy przez Pacyfik,"},
  {"tekst": "Kaca miałem już od rana,"},
  {"tekst": "No i przez to zarzygałem"},
  {"tekst": "Koję Kapitana."},
  {"tekst": ""},
  {"tekst": "Pływał z nami raz Kapitan -"},
  {"tekst": "Napalony transwestyta."},
  {"tekst": "Cała załoga wołała"},
  {"tekst": "Na niego Lolita."},
  {"tekst": ""},
  {"tekst": "Pływał z nami jeden pedał,"},
  {"tekst": "Marzył o tym całe życie,"},
  {"tekst": "Żeby zostać przedłużaczem"},
  {"tekst": "Z przodu na bukszprycie."},
  {"tekst": ""},
  {"tekst": "Znałem raz pewnego majtka,"},
  {"tekst": "Był troszeczkę nienormalny,"},
  {"tekst": "Bo uprawiał z wielorybem"},
  {"tekst": "W wodzie seks analny."},
  {"tekst": ""},
  {"tekst": "Gdy chciał wszystkim zaszpanować,"},
  {"tekst": "Rekord świata chyba pobił,"},
  {"tekst": "Jednak gdy mu kutas oklapł,"},
  {"tekst": "Dziurę w burcie zrobił.."}
]
